{
  "_job_id": "job.0712",
  "study_id": "LINC-JP",
  "analysis_id": [
    "EGAR00001106823",
    "EGAR00001106824",
    "EGAR00001106825",
    "EGAR00001106826",
    "EGAR00001106827",
    "EGAR00001106828",
    "EGAR00001106829",
    "EGAR00001106830",
    "EGAR00001106831",
    "EGAR00001106832",
    "EGAR00001106833",
    "EGAR00001116238",
    "EGAR00001116239",
    "EGAR00001116240",
    "EGAR00001116241",
    "EGAR00001116242",
    "EGAR00001117568",
    "EGAR00001117570",
    "EGAR00001117571",
    "EGAR00001117572"
  ],
  "max_retries": 3,
  "first_retry_wait_time": 60,
  "cpus": 1,
  "mem": 1,
  "local_dir": "/icgc-argo-scratch",
  "download_song_url": "https://song.cancercollaboratory.org",
  "download_score_url": "https://storage.cancercollaboratory.org",
  "download_cpus": 1,
  "download_mem": 2,
  "download_transport_mem": 2,
  "upload_song_url": "https://song.azure.icgc.overture.bio",
  "upload_score_url": "https://score.azure.icgc.overture.bio",
  "upload_cpus": 1,
  "upload_mem": 2,
  "upload_transport_mem": 2,
  "transport_mem": 2
}