{
  "_job_id": "job.0541",
  "study_id": "LINC-JP",
  "analysis_id": [
    "EGAR00001108300",
    "EGAR00001108301",
    "EGAR00001108302",
    "EGAR00001108303",
    "EGAR00001108304",
    "EGAR00001108305",
    "EGAR00001108306",
    "EGAR00001108307",
    "EGAR00001110617",
    "EGAR00001110621",
    "EGAR00001110623",
    "EGAR00001111950",
    "EGAR00001111951",
    "EGAR00001111952",
    "EGAR00001196918",
    "EGAR00001196919",
    "EGAR00001196925",
    "EGAR00001196926",
    "EGAR00001196927",
    "EGAR00001196928"
  ],
  "max_retries": 3,
  "first_retry_wait_time": 60,
  "cpus": 1,
  "mem": 1,
  "local_dir": "/icgc-argo-scratch",
  "download_song_url": "https://song.cancercollaboratory.org",
  "download_score_url": "https://storage.cancercollaboratory.org",
  "download_cpus": 1,
  "download_mem": 2,
  "download_transport_mem": 2,
  "upload_song_url": "https://song.azure.icgc.overture.bio",
  "upload_score_url": "https://score.azure.icgc.overture.bio",
  "upload_cpus": 1,
  "upload_mem": 2,
  "upload_transport_mem": 2,
  "transport_mem": 2
}