{
  "_job_id": "job.0112",
  "study_id": "LINC-JP",
  "analysis_id": [
    "EGAR00001110010",
    "EGAR00001110013",
    "EGAR00001110014",
    "EGAR00001110016",
    "EGAR00001110017",
    "EGAR00001110018",
    "EGAR00001110023",
    "EGAR00001110026",
    "EGAR00001111340",
    "EGAR00001111342",
    "EGAR00001111343",
    "EGAR00001111344",
    "EGAR00001111345",
    "EGAR00001111346",
    "EGAR00001111347",
    "EGAR00001111348",
    "EGAR00001111349",
    "EGAR00001111350",
    "EGAR00001111351",
    "EGAR00001111352",
    "EGAR00001111353",
    "EGAR00001111354",
    "EGAR00001111355",
    "EGAR00001111356",
    "EGAR00001112671",
    "EGAR00001112673",
    "EGAR00001112674",
    "EGAR00001112675",
    "EGAR00001112676",
    "EGAR00001112677",
    "EGAR00001112678",
    "EGAR00001112679",
    "EGAR00001112680",
    "EGAR00001112681",
    "EGAR00001112682",
    "EGAR00001112683",
    "EGAR00001112684",
    "EGAR00001112685",
    "EGAR00001112687",
    "EGAR00001196275",
    "EGAR00001196276",
    "EGAR00001196277",
    "EGAR00001196278",
    "EGAR00001196279",
    "EGAR00001196280",
    "EGAR00001196281",
    "EGAR00001196282",
    "EGAR00001196283",
    "EGAR00001196284",
    "EGAR00001196285"
  ],
  "max_retries": 3,
  "first_retry_wait_time": 60,
  "cpus": 1,
  "mem": 1,
  "local_dir": "/icgc-argo-scratch",
  "download_song_url": "https://song.cancercollaboratory.org",
  "download_score_url": "https://storage.cancercollaboratory.org",
  "download_cpus": 1,
  "download_mem": 2,
  "download_transport_mem": 2,
  "upload_song_url": "https://song.azure.icgc.overture.bio",
  "upload_score_url": "https://score.azure.icgc.overture.bio",
  "upload_cpus": 1,
  "upload_mem": 2,
  "upload_transport_mem": 2,
  "transport_mem": 2
}