{
  "_job_id": "job.0191",
  "study_id": "RECA-EU",
  "analysis_id": [
    "5cb971dc-d2b9-11e5-9718-a5315c6878de",
    "b6e9766e-f98b-4a99-b4f8-348c3efb037b",
    "c9dec6cf-e937-4fef-afe5-8bcf3ea7cb88",
    "ca3a4230-2dc5-4a7b-8027-e425bfe9b0b7",
    "fb37b362-1f83-40a8-bb6f-2b4889f5cbc1"
  ],
  "max_retries": 3,
  "first_retry_wait_time": 60,
  "cpus": 1,
  "mem": 1,
  "local_dir": "/icgc-argo-scratch",
  "download_song_url": "https://song.cancercollaboratory.org",
  "download_score_url": "https://storage.cancercollaboratory.org",
  "download_cpus": 1,
  "download_mem": 2,
  "download_transport_mem": 2,
  "upload_song_url": "https://song.azure.icgc.overture.bio",
  "upload_score_url": "https://score.azure.icgc.overture.bio",
  "upload_cpus": 1,
  "upload_mem": 2,
  "upload_transport_mem": 2,
  "transport_mem": 2
}